battleship/src/dflipflop.v
/*
Author:  Lab-provided code
Title: 	 D flip-flop
Summary: Behavioral model of a d flip-flop
*/

module dflipflop(q, qBar, D, clk, rst);
	input D, clk, rst; 	// DFF input, clock, reset
	output q, qBar;		// DFF output, DFF negated output
	reg q;
	not n1 (qBar, q);	// negate q
	
	// flip-flop storage logic
	always@ (negedge rst or posedge clk)
	begin
		if(!rst)
			q = 0;
		else
			q = D;
	end
endmodule

lab1/counter3/src/counter.v
`include "dflipflop.v"

module counter(out, clk, rst);
	output reg [3:0] out;
	input clk, rst;

	
	always @(posedge clk) begin
		if (!rst) begin
			out = 4'b0000;
		end else begin
			out[0] <= ~out[3];
			out[1] <= out[0];
			out[2] <= out[1];
			out[3] <= out[2];
		end
	end
endmodule

lab1/counter3/src/counterTop.v
module testBench;
	
	wire [3:0] out;
	wire clk, rst;
	
	counter myCounter(out[3:0], clk, rst);
	Tester aTester(out[3:0], clk, rst);


	initial 
	begin
		$dumpfile("counter.vcd");
		$dumpvars(1, myCounter);
	end
	
	
endmodule



module Tester(out, clk, rst);
	input [3:0] out;
	output reg clk, rst;
	
	parameter stimDelay = 20;
	
	initial
	begin	
		$display("\t\t bits \t clk \t rst");
		$monitor("\t\t %b\t %b\t %b", out, rst, clk);
	end
	
	integer i;
	initial
	begin
		#stimDelay;
		rst = 'b0; clk = 'b0;
		#stimDelay clk = 'b1;
		#stimDelay clk = 'b0; rst = 'b1;
		
		// 4 iterations to test reset
		for (i = 0; i < 3; i = i + 1) begin
			#stimDelay clk = 'b1;
			#stimDelay clk = 'b0;
		end
		rst = 'b0;
		#stimDelay clk = 'b1;
		#stimDelay clk = 'b0;  rst = 'b1;
		
		// 16 iterations to test counter
		for (i=0; i < 15; i = i + 1) begin
			#stimDelay clk = 'b1;
			#stimDelay clk = 'b0;
		end
		
		#stimDelay clk = 'b1;
		#stimDelay clk = 'b0;
		
		#(2*stimDelay);
		$finish;
	end

endmodule

lab1/counter3/src/counter.vcd
$date
	Thu Apr 07 15:50:16 2016
$end
$version
	Icarus Verilog
$end
$timescale
	1s
$end
$scope module testBench $end
$scope module myCounter $end
$var wire 1 ! clk $end
$var wire 1 " rst $end
$var reg 4 # out [3:0] $end
$upscope $end
$upscope $end
$enddefinitions $end
#0
$dumpvars
bx #
x"
x!
$end
#20
0!
0"
#40
b0 #
1!
#60
1"
0!
#80
b1 #
1!
#100
0!
#120
b11 #
1!
#140
0!
#160
b111 #
1!
#180
0"
0!
#200
b0 #
1!
#220
1"
0!
#240
b1 #
1!
#260
0!
#280
b11 #
1!
#300
0!
#320
b111 #
1!
#340
0!
#360
b1111 #
1!
#380
0!
#400
b1110 #
1!
#420
0!
#440
b1100 #
1!
#460
0!
#480
b1000 #
1!
#500
0!
#520
b0 #
1!
#540
0!
#560
b1 #
1!
#580
0!
#600
b11 #
1!
#620
0!
#640
b111 #
1!
#660
0!
#680
b1111 #
1!
#700
0!
#720
b1110 #
1!
#740
0!
#760
b1100 #
1!
#780
0!
#800
b1000 #
1!
#820
0!
#840
b0 #
1!
