battleship/src/dflipflop.v
/*
Author:  Lab-provided code
Title: 	 D flip-flop
Summary: Behavioral model of a d flip-flop
*/

module dflipflop(q, qBar, D, clk, rst);
	input D, clk, rst; 	// DFF input, clock, reset
	output q, qBar;		// DFF output, DFF negated output
	reg q;
	not n1 (qBar, q);	// negate q
	
	// flip-flop storage logic
	always@ (negedge rst or posedge clk)
	begin
		if(!rst)
			q = 0;
		else
			q = D;
	end
endmodule

lab1/counter2/src/DFlipFlop.v
/*
Author:  Lab-provided code
Title: 	 D flip-flop
Summary: Behavioral model of a d flip-flop
*/

module DFlipFlop(q, qBar, D, clk, rst);
	input D, clk, rst; 	// DFF input, clock, reset
	output q, qBar;		// DFF output, DFF negated output
	reg q;
	not n1 (qBar, q);	// negate q
	
	// flip-flop storage logic
	always@ (negedge rst or posedge clk)
	begin
		if(!rst)
			q = 0;
		else
			q = D;
	end
endmodule

lab1/counter2/src/counter.v
`include "dflipflop.v"

module counter(out, clk, rst);
	output wire [3:0] out;
	input clk, rst;
	wire [3:0] PS, NS, PS_n;
	

	DFlipFlop dff0(PS[0], PS_n[0], NS[0], clk, rst);
	DFlipFlop dff1(PS[1], PS_n[1], NS[1], clk, rst);
	DFlipFlop dff2(PS[2], PS_n[2], NS[2], clk, rst);
	DFlipFlop dff3(PS[3], PS_n[3], NS[3], clk, rst);

	assign out = PS;
	assign NS[0] = PS_n[0];
	assign NS[1] = PS[0] & PS[1] | PS_n[0] & PS_n[1];
	assign NS[2] = PS[2] & PS[0] | PS[2] & PS[1] | PS_n[2] & PS_n[1] & PS_n[0];
	assign NS[3] = PS[3] & PS[2] | PS[3] & PS[1] | PS[3] & PS[0] | PS_n[3] & PS_n[2] & PS_n[1] & PS_n[0];

endmodule

lab1/counter2/src/counterTop.v
`include "counter.v"

module testBench;
	
	wire [3:0] out;
	wire clk, rst;
	
	counter myCounter(out[3:0], clk, rst);
	Tester aTester(out[3:0], clk, rst);


	initial 
	begin
		$dumpfile("counter.vcd");
		$dumpvars(1, myCounter);
	end
	
	
endmodule



module Tester(out, clk, rst);
	input [3:0] out;
	output reg clk, rst;
	
	parameter stimDelay = 20;
	
	initial
	begin	
		$display("\t\t bits \t clk \t rst");
		$monitor("\t\t %b\t %b\t %b", out, clk, rst);
	end
	
	integer i;
	initial
	begin
		#stimDelay;
		rst = 'b0; clk = 'b0;
		#stimDelay clk = 'b1;
		#stimDelay clk = 'b0; rst = 'b1;
		
		// 4 iterations to test reset
		for (i = 0; i < 3; i = i + 1) begin
			#stimDelay clk = 'b1;
			#stimDelay clk = 'b0;
		end
		rst = 'b0;
		#stimDelay clk = 'b1;
		#stimDelay clk = 'b0;  rst = 'b1;
		
		// 16 iterations to test counter
		for (i=0; i < 15; i = i + 1) begin
			#stimDelay clk = 'b1;
			#stimDelay clk = 'b0;
		end
		
		#stimDelay clk = 'b1;
		#stimDelay clk = 'b0;
		
		#(2*stimDelay);
		$finish;
	end

endmodule

lab1/counter2/src/counter.vcd
$date
	Thu Apr 07 15:20:02 2016
$end
$version
	Icarus Verilog
$end
$timescale
	1s
$end
$scope module testBench $end
$scope module myCounter $end
$var wire 1 ! clk $end
$var wire 4 " out [3:0] $end
$var wire 1 # rst $end
$var wire 4 $ PS_n [3:0] $end
$var wire 4 % PS [3:0] $end
$var wire 4 & NS [3:0] $end
$upscope $end
$upscope $end
$enddefinitions $end
#0
$dumpvars
bx &
bx %
bx $
x#
bx "
x!
$end
#20
b1111 &
b1111 $
b0 "
b0 %
0!
0#
#40
1!
#60
1#
0!
#80
b1110 &
b0 $
b1111 "
b1111 %
1!
#100
0!
#120
b1101 &
b1 $
b1110 "
b1110 %
1!
#140
0!
#160
b1100 &
b10 $
b1101 "
b1101 %
1!
#180
b1111 &
b1111 $
b0 "
b0 %
0#
0!
#200
1!
#220
1#
0!
#240
b1110 &
b0 $
b1111 "
b1111 %
1!
#260
0!
#280
b1101 &
b1 $
b1110 "
b1110 %
1!
#300
0!
#320
b1100 &
b10 $
b1101 "
b1101 %
1!
#340
0!
#360
b1011 &
b11 $
b1100 "
b1100 %
1!
#380
0!
#400
b1010 &
b100 $
b1011 "
b1011 %
1!
#420
0!
#440
b1001 &
b101 $
b1010 "
b1010 %
1!
#460
0!
#480
b1000 &
b110 $
b1001 "
b1001 %
1!
#500
0!
#520
b111 &
b111 $
b1000 "
b1000 %
1!
#540
0!
#560
b110 &
b1000 $
b111 "
b111 %
1!
#580
0!
#600
b101 &
b1001 $
b110 "
b110 %
1!
#620
0!
#640
b100 &
b1010 $
b101 "
b101 %
1!
#660
0!
#680
b11 &
b1011 $
b100 "
b100 %
1!
#700
0!
#720
b10 &
b1100 $
b11 "
b11 %
1!
#740
0!
#760
b1 &
b1101 $
b10 "
b10 %
1!
#780
0!
#800
b0 &
b1110 $
b1 "
b1 %
1!
#820
0!
#840
b1111 &
b1111 $
b0 "
b0 %
1!
