lab1/counter2/src/DFlipFlop.v
/*
Author:  Lab-provided code
Title: 	 D flip-flop
Summary: Behavioral model of a d flip-flop
*/

module DFlipFlop(q, qBar, D, clk, rst);
	input D, clk, rst; 	// DFF input, clock, reset
	output q, qBar;		// DFF output, DFF negated output
	reg q;
	not n1 (qBar, q);	// negate q
	
	// flip-flop storage logic
	always@ (negedge rst or posedge clk)
	begin
		if(!rst)
			q = 0;
		else
			q = D;
	end
endmodule

lab1/counter1/src/counter.v
module counter(out, clk, rst)
	output [3:0] out;
	input clk, reset;
	wire [3:0] qbar;
	
	DFlipFlop dff0(out[0], qbar[0], qbar[0], clk, rst);
	DFlipFlop dff1(out[1], qbar[1], qbar[1], out[0], rst);
	DFlipFlop dff1(out[2], qbar[1], qbar[1], out[1], rst);
	DFlipFlop dff1(out[3], qbar[1], qbar[1], out[2], rst);
	
endmodule;

lab1/counter1/src/counterTop.v
/*
Author:  Katie Neff
Title: 	 testBench
Summary: Test bench module that drives the tests for a counter 
*/

module testBench;
	
	wire [3:0] out;
	wire clk, rst;
	
	// Declare an instance of the counter module
	counter myCounter(out[3:0], clk, rst);
	
	// Declare an instance of the Tester module
	Tester aTester(out[3:0], clk, rst);

	// File for gtkwave
	initial 
	begin
		$dumpfile("counter.vcd");
		$dumpvars(1, myCounter);
	end
	
	
endmodule


/*
Author:  Katie Neff
Title: 	 Tester
Summary: Testing module for the counter to show what it is counting.
*/

module Tester(out, clk, rst);
	input [3:0] out; // 4-bit data of the counter as input
	output reg clk, rst; // Clock and Reset for the counters
	
	parameter stimDelay = 20;
	
	initial
	begin	
		// Displays the data and labels for the counter
		$display("\t\t bits \t rst \t clk");
		$monitor("\t\t %b\t %b\t %b", out, rst, clk);
	end
	
	integer i;
	initial
	begin
		#stimDelay;
		rst = 'b0; clk = 'b0;
		#stimDelay clk = 'b1;
		#stimDelay clk = 'b0; rst = 'b1;
		
		// 4 iterations to test reset
		for (i = 0; i < 4; i = i + 1) begin
			#stimDelay clk = 'b1;
			#stimDelay clk = 'b0;
		end
		rst = 'b0;
		#stimDelay clk = 'b1;
		#stimDelay clk = 'b0;  rst = 'b1;
		
		// 16 iterations to test counter
		for (i=0; i < 16; i = i + 1) begin
			#stimDelay clk = 'b1;
			#stimDelay clk = 'b0;
		end
		
		#stimDelay clk = 'b1;
		#stimDelay clk = 'b0;
		
		#(2*stimDelay);
		$finish;
	end

endmodule

lab1/counter1/src/counter.vcd
$date
	Wed Apr 06 17:54:47 2016
$end
$version
	Icarus Verilog
$end
$timescale
	1s
$end
$scope module testBench $end
$scope module myCounter $end
$var wire 1 ! clk $end
$var wire 1 " rst $end
$var wire 4 # qbar [3:0] $end
$var wire 4 $ out [3:0] $end
$upscope $end
$upscope $end
$enddefinitions $end
#0
$dumpvars
bx $
bx #
x"
x!
$end
#20
b1111 #
b0 $
0!
0"
#40
1!
#60
1"
0!
#80
b0 #
b1111 $
1!
#100
0!
#120
b1 #
b1110 $
1!
#140
0!
#160
b10 #
b1101 $
1!
#180
b1111 #
b0 $
0"
0!
#200
1!
#220
1"
0!
#240
b0 #
b1111 $
1!
#260
0!
#280
b1 #
b1110 $
1!
#300
0!
#320
b10 #
b1101 $
1!
#340
0!
#360
b11 #
b1100 $
1!
#380
0!
#400
b100 #
b1011 $
1!
#420
0!
#440
b101 #
b1010 $
1!
#460
0!
#480
b110 #
b1001 $
1!
#500
0!
#520
b111 #
b1000 $
1!
#540
0!
#560
b1000 #
b111 $
1!
#580
0!
#600
b1001 #
b110 $
1!
#620
0!
#640
b1010 #
b101 $
1!
#660
0!
#680
b1011 #
b100 $
1!
#700
0!
#720
b1100 #
b11 $
1!
#740
0!
#760
b1101 #
b10 $
1!
#780
0!
#800
b1110 #
b1 $
1!
#820
0!
#840
b1111 #
b0 $
1!
